README.md
setup.cfg
setup.py
torch_mimicry/__init__.py
torch_mimicry.egg-info/PKG-INFO
torch_mimicry.egg-info/SOURCES.txt
torch_mimicry.egg-info/dependency_links.txt
torch_mimicry.egg-info/requires.txt
torch_mimicry.egg-info/top_level.txt
torch_mimicry/datasets/__init__.py
torch_mimicry/datasets/data_utils.py
torch_mimicry/datasets/image_loader.py
torch_mimicry/datasets/imagenet/__init__.py
torch_mimicry/datasets/imagenet/imagenet.py
torch_mimicry/datasets/imagenet/imagenet_utils.py
torch_mimicry/metrics/__init__.py
torch_mimicry/metrics/compute_fid.py
torch_mimicry/metrics/compute_is.py
torch_mimicry/metrics/compute_kid.py
torch_mimicry/metrics/compute_metrics.py
torch_mimicry/metrics/fid/__init__.py
torch_mimicry/metrics/fid/fid_utils.py
torch_mimicry/metrics/inception_model/__init__.py
torch_mimicry/metrics/inception_model/inception_utils.py
torch_mimicry/metrics/inception_score/__init__.py
torch_mimicry/metrics/inception_score/inception_score_utils.py
torch_mimicry/metrics/kid/__init__.py
torch_mimicry/metrics/kid/kid_utils.py
torch_mimicry/modules/__init__.py
torch_mimicry/modules/biggan_resblocks.py
torch_mimicry/modules/layers.py
torch_mimicry/modules/losses.py
torch_mimicry/modules/resblocks.py
torch_mimicry/modules/spectral_norm.py
torch_mimicry/nets/__init__.py
torch_mimicry/nets/basemodel/__init__.py
torch_mimicry/nets/basemodel/basemodel.py
torch_mimicry/nets/cgan_pd/__init__.py
torch_mimicry/nets/cgan_pd/cgan_pd_128.py
torch_mimicry/nets/cgan_pd/cgan_pd_32.py
torch_mimicry/nets/cgan_pd/cgan_pd_base.py
torch_mimicry/nets/dcgan/__init__.py
torch_mimicry/nets/dcgan/dcgan_128.py
torch_mimicry/nets/dcgan/dcgan_32.py
torch_mimicry/nets/dcgan/dcgan_48.py
torch_mimicry/nets/dcgan/dcgan_64.py
torch_mimicry/nets/dcgan/dcgan_base.py
torch_mimicry/nets/dcgan/dcgan_cifar.py
torch_mimicry/nets/gan/__init__.py
torch_mimicry/nets/gan/cgan.py
torch_mimicry/nets/gan/gan.py
torch_mimicry/nets/infomax_gan/__init__.py
torch_mimicry/nets/infomax_gan/infomax_gan_128.py
torch_mimicry/nets/infomax_gan/infomax_gan_32.py
torch_mimicry/nets/infomax_gan/infomax_gan_48.py
torch_mimicry/nets/infomax_gan/infomax_gan_64.py
