Metadata-Version: 2.1
Name: torch-mimicry
Version: 0.1.16
Summary: Mimicry: Towards the Reproducibility of GAN Research
Home-page: https://github.com/kwotsin/mimicry
Author: Kwot Sin Lee
Author-email: ksl36@cam.ac.uk
License: UNKNOWN
Download-URL: https://github.com/kwotsin/mimicry/archive/0.1.16.tar.gz
Keywords: pytorch,generative-adversarial-networks,gans,GAN
Platform: UNKNOWN
Requires-Python: >=3.6
